{
    "data": [
      {
        "image": "car-01.jpg",
        "car": "Ford Endeavour",
        "carType": "Sedan",
        "baseLocation": "Newyork City",
        "price": "$3500",
        "damages": "01",
        "createdDate": "25 May 2025",
        "status": "Active"
      },
      {
        "image": "car-02.jpg",
        "car": "Ferrari 458 MM",
        "carType": "Convertible",
        "baseLocation": "Los Angeles",
        "price": "$2800",
        "damages": "05",
        "createdDate": "25 May 2025",
        "status": "Inactive"
      },
      {
        "image": "car-03.jpg",
        "car": "Ford Mustang",
        "carType": "Coupe",
        "baseLocation": "Chicago",
        "price": "$1425",
        "damages": "05",
        "isFilled":false,
        "createdDate": "25 May 2025",
        "status": "Active"
      },
      {
        "image": "car-04.jpg",
        "car": "Toyota Tacoma 4",
        "carType": "Hatchback",
        "baseLocation": "Houston",
        "price": "$745",
        "damages": "04",
        "createdDate": "25 May 2025",
        "status": "Active"
      },
      {
        "image": "car-05.jpg",
        "car": "Chevrolet Pick",
        "carType": "Sedan",
        "baseLocation": "Phoenix",
        "price": "$659",
        "damages": "02",
        "createdDate": "25 May 2025",
        "status": "Active"
      },
      {
        "image": "car-06.jpg",
        "car": "Etios Carmen",
        "carType": "Hatchback",
        "baseLocation": "Philadelphia",
        "price": "$254",
        "isFilled":false,
        "damages": "01",
        "createdDate": "25 May 2025",
        "status": "Active"
      },
      {
        "image": "car-07.jpg",
        "car": "Acura Sport Version",
        "carType": "Crossover",
        "baseLocation": "Austin",
        "price": "$1240",
        "damages": "5",
        "createdDate": "25 May 2025",
        "status": "Active"
      },
      {
        "image": "car-08.jpg",
        "car": "Kia Soul 2016",
        "carType": "Station Wagon",
        "baseLocation": "San Antonio",
        "price": "$1425",
        "damages": "02",
        "createdDate": "25 May 2025",
        "status": "Active"
      },
      {
        "image": "car-11.jpg",
        "car": "Chevrolet Camaro",
        "carType": "Station Wagon",
        "baseLocation": "Los Angeles",
        "price": "$4124",
        "isFilled":false,
        "damages": "03",
        "createdDate": "25 May 2025",
        "status": "Inactive"
      },
      {
        "image": "car-10.jpg",
        "car": "Toyota Camry SE 350",
        "carType": "Mini Van",
        "baseLocation": "Chicago",
        "price": "$4741",
        "damages": "02",
        "createdDate": "25 May 2025",
        "status": "Active"
      }
    ],
    "totalData": 10
  }
  