{
    "data" : [        
          {
            "MENU": "Footer 1",
            "CREATEDDATE": "24 Jan 2025",
            "STATUS": "Unpublished"
          },
          {
            "MENU": "Footer 2",
            "CREATEDDATE": "24 Jan 2025",
            "STATUS": "Published"
          },
          {
            "MENU": "Footer 3",
            "CREATEDDATE": "24 Jan 2025",
            "STATUS": "Published"
          },
          {
            "MENU": "Footer 4",
            "CREATEDDATE": "24 Jan 2025",
            "STATUS": "Published"
          },
          {
            "MENU": "Header Top",
            "CREATEDDATE": "24 Jan 2025",
            "STATUS": "Published"
          }
    ],
    "totalData": 5
}